.gitignore
README.md
a.py
ode.md
setup.py
Integral.egg-info/PKG-INFO
Integral.egg-info/SOURCES.txt
Integral.egg-info/dependency_links.txt
Integral.egg-info/requires.txt
Integral.egg-info/top_level.txt
docs/Makefile
docs/conf.py
docs/index.rst
docs/make.bat
docs/apis/integration.rst
integral/__init__.py
integral/diff_eq.py
integral/profile.py
integral/state.py
integral/backend/__init__.py
integral/backend/_numpy_gpu.py
integral/backend/generate_overloads.py
integral/backend/numba_overloads.py
integral/dde/__init__.py
integral/delay_fde/__init__.py
integral/delay_fde/abm_methods.py
integral/fde/__init__.py
integral/ode/__init__.py
integral/ode/adaptive_methods.py
integral/ode/implicit_methods.py
integral/ode/other_methods.py
integral/ode/runge_kutta_methods.py
integral/ode/tests.py
integral/sde/__init__.py
integral/sde/other_methods.py
integral/sde/srk_scalar.py
integral/sde/srk_strong.py
integral/sde/srk_weak.py